Workbook

Sheet 📋 Capa
B1: HEALTH INSURANCE
B4: Análise de Segmentação de Clientes com Machine Learning
B6: Impacto de Perfis de Clientes nos Custos com Saúde
B7: ▌ SOBRE O PROJETO
B8: Este projeto utiliza Machine Learning (K-Means Clustering) para segmentar 1.338 clientes de plano de saúde em 4 grupos homogêneos com base em perfil demográfico e histórico de custos. O objetivo é otimizar a precificação dos prêmios de seguro, garantindo margens de lucro adequadas para cada segmento de risco.
B11: ▌ SEGMENTOS IDENTIFICADOS
B12: CLUSTER 0 — Jovens Saudáveis
B13: 414 clientes • Idade ≈ 26 anos • IMC ≈ 22.8 • Custo ≈ R$ 1.884 • Margem: 15% → Prêmio Alvo: R$ 2.513
B14: CLUSTER 1 — Alto Risco (Idade/IMC)
B15: 356 clientes • Idade ≈ 53 anos • IMC ≈ 31.9 • Custo ≈ R$ 4.746 • Margem: -5% ⚠️ → Prêmio Alvo: R$ 6.328
B16: CLUSTER 2 — Família Numerosa
B17: 294 clientes • Idade ≈ 41 anos • Filhos ≈ 2.7 • Custo ≈ R$ 2.133 • Margem: 25% → Prêmio Alvo: R$ 3.047
... B20: ▌ ESTRUTURA DO PROJETO
B21: Base_Clientes | E21: Base de dados bruta com 1.338 clientes e variáveis demográficas + custos médicos
B22: Clusterização_com_Python | E22: Documentação completa do processo K-Means: padronização, método cotovelo e clusterização
B23: Base_Clusterizada | E23: Base final com a coluna 'Cluster' atribuída a cada cliente
B24: Análises | E24: Métricas estatísticas por cluster, interpretações e cálculo do Prêmio Alvo
B25: Quanto_Cobrar | E25: Simulação individual: prêmio atual vs. prêmio alvo vs. lucro por cliente
B26: Novos_Clientes | E26: Classificação automática de novos clientes com atribuição de prêmio alvo
B27: ▌ ❓ PERGUNTAS DE NEGÓCIO
B28: 1. É possível identificar perfis de clientes de menor risco e menor custo para apoiar estratégias de marketing e seleção? | E28: O Cluster 0 (Jovens Saudáveis) é o perfil de menor risco: ~26 anos, IMC ~22,8, sem filhos, custo médio de R$ 1.884. Ideal para ações de marketing e fidelização.
B29: 2. Clientes elegíveis a desconto realmente apresentam menor risco? | E29: Não necessariamente. O Cluster 3 agrupa 100% dos clientes com desconto, mas ainda gera custo médio de R$ 2.576 com margem de apenas 9% — não são os de menor risco, apenas os de risco moderado.
B30: 3. Como precificar o prêmio dos clientes para minimizar o risco e aumentar a lucratividade? | E30: Ajustando o prêmio por cluster conforme o risco real: Cluster 0 → R$ 2.513 (margem 15%) Cluster 1 → R$ 6.328 (margem -5% atual, urgente reajuste) Cluster 2 → R$ 3.047 (margem 25%) Cluster 3 → R$ 3.220 (margem 9%)

Sheet 📂 base_clientes
A1: age | B1: gender | C1: bmi | D1: children | E1: discount_eligibility | F1: region | G1: expenses | H1: premium | I1: discount_eligibility_tratado
A2: 19 | B2: female | C2: 24.1 | D2: 0 | E2: yes | F2: south | G2: 1483.2083 | H2: 1744.951 | I2: =IF(base_clientes[[#This Row],[discount_eligibility]]="yes",1,0) -> 1
A3: 18 | B3: male | C3: 23.5 | D3: 1 | E3: no | F3: southeast | G3: 2237.6079 | H3: 2632.4799 | I3: =IF(base_clientes[[#This Row],[discount_eligibility]]="yes",1,0) -> 0
A4: 28 | B4: male | C4: 33 | D4: 3 | E4: no | F4: southeast | G4: 2046.0872 | H4: 2728.1162 | I4: =IF(base_clientes[[#This Row],[discount_eligibility]]="yes",1,0) -> 0
A5: 33 | B5: male | C5: 23.3 | D5: 0 | E5: no | F5: midwest | G5: 2331.692 | H5: 2743.1671 | I5: =IF(base_clientes[[#This Row],[discount_eligibility]]="yes",1,0) -> 0
A6: 32 | B6: male | C6: 23.4 | D6: 0 | E6: no | F6: midwest | G6: 1942.5013 | H6: 2285.2956 | I6: =IF(base_clientes[[#This Row],[discount_eligibility]]="yes",1,0) -> 0
A7: 31 | B7: female | C7: 22.9 | D7: 0 | E7: no | F7: southeast | G7: 2375.7405 | H7: 2794.9889 | I7: =IF(base_clientes[[#This Row],[discount_eligibility]]="yes",1,0) -> 0
A8: 46 | B8: female | C8: 33.4 | D8: 1 | E8: no | F8: southeast | G8: 4453.2339 | H8: 4241.1752 | I8: =IF(base_clientes[[#This Row],[discount_eligibility]]="yes",1,0) -> 0
A9: 37 | B9: female | C9: 27.7 | D9: 3 | E9: no | F9: midwest | G9: 2326.6882 | H9: 3102.2509 | I9: =IF(base_clientes[[#This Row],[discount_eligibility]]="yes",1,0) -> 0
A10: 37 | B10: male | C10: 29.8 | D10: 2 | E10: no | F10: northeast | G10: 1712.426 | H10: 2283.2346 | I10: =IF(base_clientes[[#This Row],[discount_eligibility]]="yes",1,0) -> 0
A11: 60 | B11: female | C11: 25.8 | D11: 0 | E11: no | F11: midwest | G11: 4684.8206 | H11: 4461.7339 | I11: =IF(base_clientes[[#This Row],[discount_eligibility]]="yes",1,0) -> 0
A12: 25 | B12: male | C12: 20.3 | D12: 0 | E12: no | F12: northeast | G12: 2168.5565 | H12: 2551.2429 | I12: =IF(base_clientes[[#This Row],[discount_eligibility]]="yes",1,0) -> 0
A13: 62 | B13: female | C13: 26.3 | D13: 0 | E13: yes | F13: southeast | G13: 5417.6353 | H13: 5159.6527 | I13: =IF(base_clientes[[#This Row],[discount_eligibility]]="yes",1,0) -> 1
... A1339: 61 | B1339: female | C1339: 29.1 | D1339: 0 | E1339: yes | F1339: midwest | G1339: 4541.902 | H1339: 4325.6209 | I1339: =IF(base_clientes[[#This Row],[discount_eligibility]]="yes",1,0) -> 1

Sheet 🐍 Clusterização_Python
A1: CLUSTERIZAÇÃO K-MEANS — DOCUMENTAÇÃO DO PROCESSO
A3: 1 — Carregar tabela do Excel para o Python | E3: {=_xlfn._xlws.PY(0,1,base_clientes[#All])} -> #VALUE!
A4: 2 — Padronizar os dados (StandardScaler) | E4: {=_xlfn._xlws.PY(1,1)} -> #VALUE!
A5: 3 — Avaliar quantidade de clusters | E5: {=_xlfn._xlws.PY(2,0)} -> #VALUE!
A25: 4 — Executar a Clusterização (K-Means, k=4) | E25: {=_xlfn._xlws.PY(3,1)} -> #VALUE!
A26: 5 — Adicionar coluna 'Cluster' à base | E26: {=_xlfn._xlws.PY(4,1)} -> 0
A27: 6 — Exibir base clusterizada | E27: {=_xlfn._xlws.PY(5,0)} -> age | F27: gender | G27: bmi | H27: children | I27: discount_eligibility | J27: region | K27: expenses | L27: premium | M27: discount_eligibility_tratado | N27: Clusters
E28: 19 | F28: female | G28: 24.1 | H28: 0 | I28: yes | J28: south | K28: 1483.2083 | L28: 1744.951 | M28: 1 | N28: 3
E29: 18 | F29: male | G29: 23.5 | H29: 1 | I29: no | J29: southeast | K29: 2237.6079 | L29: 2632.4799 | M29: 0 | N29: 0
E30: 28 | F30: male | G30: 33 | H30: 3 | I30: no | J30: southeast | K30: 2046.0872 | L30: 2728.1162 | M30: 0 | N30: 2
E31: 33 | F31: male | G31: 23.3 | H31: 0 | I31: no | J31: midwest | K31: 2331.692 | L31: 2743.1671 | M31: 0 | N31: 0
E32: 32 | F32: male | G32: 23.4 | H32: 0 | I32: no | J32: midwest | K32: 1942.5013 | L32: 2285.2956 | M32: 0 | N32: 0
E33: 31 | F33: female | G33: 22.9 | H33: 0 | I33: no | J33: southeast | K33: 2375.7405 | L33: 2794.9889 | M33: 0 | N33: 0
E34: 46 | F34: female | G34: 33.4 | H34: 1 | I34: no | J34: southeast | K34: 4453.2339 | L34: 4241.1752 | M34: 0 | N34: 1
E35: 37 | F35: female | G35: 27.7 | H35: 3 | I35: no | J35: midwest | K35: 2326.6882 | L35: 3102.2509 | M35: 0 | N35: 2
E36: 37 | F36: male | G36: 29.8 | H36: 2 | I36: no | J36: northeast | K36: 1712.426 | L36: 2283.2346 | M36: 0 | N36: 2
E37: 60 | F37: female | G37: 25.8 | H37: 0 | I37: no | J37: midwest | K37: 4684.8206 | L37: 4461.7339 | M37: 0 | N37: 1
E38: 25 | F38: male | G38: 20.3 | H38: 0 | I38: no | J38: northeast | K38: 2168.5565 | L38: 2551.2429 | M38: 0 | N38: 0
E39: 62 | F39: female | G39: 26.3 | H39: 0 | I39: yes | J39: southeast | K39: 5417.6353 | L39: 5159.6527 | M39: 1 | N39: 3
... E1365: 61 | F1365: female | G1365: 29.1 | H1365: 0 | I1365: yes | J1365: midwest | K1365: 4541.902 | L1365: 4325.6209 | M1365: 1 | N1365: 3

Sheet 🗄️ Base_Clusterizada
A1: Idade | B1: Gênero | C1: IMC | D1: Nº Filhos | E1: Elegível Desconto | F1: Região | G1: Custos Médicos (R$) | H1: Prêmio (R$) | I1: Desconto (0/1) | J1: Cluster
A2: 19 | B2: female | C2: 24.1 | D2: 0 | E2: yes | F2: south | G2: 1483.2083 | H2: 1744.951 | I2: 1 | J2: 3
A3: 18 | B3: male | C3: 23.5 | D3: 1 | E3: no | F3: southeast | G3: 2237.6079 | H3: 2632.4799 | I3: 0 | J3: 0
A4: 28 | B4: male | C4: 33 | D4: 3 | E4: no | F4: southeast | G4: 2046.0872 | H4: 2728.1162 | I4: 0 | J4: 2
A5: 33 | B5: male | C5: 23.3 | D5: 0 | E5: no | F5: midwest | G5: 2331.692 | H5: 2743.1671 | I5: 0 | J5: 0
A6: 32 | B6: male | C6: 23.4 | D6: 0 | E6: no | F6: midwest | G6: 1942.5013 | H6: 2285.2956 | I6: 0 | J6: 0
A7: 31 | B7: female | C7: 22.9 | D7: 0 | E7: no | F7: southeast | G7: 2375.7405 | H7: 2794.9889 | I7: 0 | J7: 0
A8: 46 | B8: female | C8: 33.4 | D8: 1 | E8: no | F8: southeast | G8: 4453.2339 | H8: 4241.1752 | I8: 0 | J8: 1
A9: 37 | B9: female | C9: 27.7 | D9: 3 | E9: no | F9: midwest | G9: 2326.6882 | H9: 3102.2509 | I9: 0 | J9: 2
A10: 37 | B10: male | C10: 29.8 | D10: 2 | E10: no | F10: northeast | G10: 1712.426 | H10: 2283.2346 | I10: 0 | J10: 2
A11: 60 | B11: female | C11: 25.8 | D11: 0 | E11: no | F11: midwest | G11: 4684.8206 | H11: 4461.7339 | I11: 0 | J11: 1
A12: 25 | B12: male | C12: 20.3 | D12: 0 | E12: no | F12: northeast | G12: 2168.5565 | H12: 2551.2429 | I12: 0 | J12: 0
A13: 62 | B13: female | C13: 26.3 | D13: 0 | E13: yes | F13: southeast | G13: 5417.6353 | H13: 5159.6527 | I13: 1 | J13: 3
... A1339: 61 | B1339: female | C1339: 29.1 | D1339: 0 | E1339: yes | F1339: midwest | G1339: 4541.902 | H1339: 4325.6209 | I1339: 1 | J1339: 3

Sheet 📊 Análises
A1: 📊 ANÁLISE DE CLUSTERS — HEALTH INSURANCE
A3: Segmentação de 1.338 clientes em 4 grupos homogêneos via K-Means para precificação diferenciada de planos de saúde
A4: ▌ MÉTRICAS POR CLUSTERS
A5: Rótulos de Linha | B5: Idade Média | C5: IMC Médio | D5: Nº Filhos | E5: Custo Médio (R$) | F5: Desvio Padrão | G5: Prêmio Médio (R$) | H5: Coeficiente de Varição | I5: Lucro Médio (R$) | J5: Margem Atual | K5: Margem Desejada
A6: 0 | B6: 26.26087 | C6: 22.836473 | D6: 0.52657005 | E6: 1884.3978 | F6: 327.96113 | G6: 2216.9386 | H6: =F6/E6 -> 0.17404029 | I6: =G6-E6 -> 332.54079 | J6: =I6/G6 -> 0.15 | K6: 0.25
A7: 1 | B7: 52.865169 | C7: 31.853371 | D7: 0.40730337 | E7: 4746.0311 | F7: 700.78381 | G7: 4525.8007 | H7: =F7/E7 -> 0.14765681 | I7: =G7-E7 -> -220.23038 | J7: =I7/G7 -> -0.048661085 | K7: 0.25
A8: 2 | B8: 41.544218 | C8: 31.680612 | D8: 2.7108844 | E8: 2133.1157 | F8: 682.64756 | G8: 2844.1542 | H8: =F8/E8 -> 0.3200237 | I8: =G8-E8 -> 711.03855 | J8: =I8/G8 -> 0.25 | K8: 0.3
A9: 3 | B9: 38.514599 | C9: 28.054745 | D9: 1.1131387 | E9: 2576.1859 | F9: 1375.2247 | G9: 2832.5492 | H9: =F9/E9 -> 0.53382198 | I9: =G9-E9 -> 256.36331 | J9: =I9/G9 -> 0.090506216 | K9: 0.2
A10: Total Geral | B10: 39.207025 | C10: 28.247534 | D10: 1.0949178 | E10: 2842.1067 | F10: 1423.4306 | G10: 3095.1401 | J10: — | K10: —
A12: ▌ INTERPRETAÇÃO DOS CLUSTERS
A13: CLUSTER 0 — Jovens Saudáveis
A14: Perfil mais jovem (≈26 anos), IMC saudável (≈22.8) e poucos filhos. Custo médico baixo com baixo desvio-padrão: grupo previsível. Margem de 15% — há espaço para crescer com pricing otimizado.
A16: CLUSTER 1 — Alto Risco (Idade/IMC)
A17: Perfil mais velho (≈53 anos) com IMC elevado (≈31.9). Custos altos (~R$ 4.746) e prêmio atual ABAIXO do custo — margem NEGATIVA de -4.9%. AÇÃO URGENTE: repricing necessário.
A19: CLUSTER 2 — Família Numerosa
A20: Meia-idade (≈41 anos), IMC moderado-alto e ≈2.7 filhos em média. CV elevado (32%) indica heterogeneidade. Margem saudável de 25%, mas requer atenção ao risco de filhos.
A22: CLUSTER 3 — Clientes com Desconto
A23: 100% elegíveis a desconto. Perfil misto com alto CV de custos (53%) — grupo muito heterogêneo. Margem atual apenas 9%. Meta de 20% requer revisão da política de descontos.
A25: ▌ PREÇO ALVO POR CLUSTER (com margem desejada)
A26: Cluster | B26: Perfil | C26: Custo Médio (R$) | D26: Margem Atual | E26: Margem Desejada | F26: Prêmio Atual (R$) | G26: Preço Alvo (R$) | H26: Δ Ajuste (R$)
A27: 0 | B27: Jovens Saudáveis | C27: =E6 -> 1884.3978 | D27: =J6 -> 0.15 | E27: =K6 -> 0.25 | F27: =G6 -> 2216.9386 | G27: =C27/(1-E27) -> 2512.5304 | H27: =G27-F27 -> 295.59181
A28: 1 | B28: Alto Risco | C28: =E7 -> 4746.0311 | D28: =J7 -> -0.048661085 | E28: =K7 -> 0.25 | F28: =G7 -> 4525.8007 | G28: =C28/(1-E28) -> 6328.0415 | H28: =G28-F28 -> 1802.2407
A29: 2 | B29: Família Numerosa | C29: =E8 -> 2133.1157 | D29: =J8 -> 0.25 | E29: =K8 -> 0.3 | F29: =G8 -> 2844.1542 | G29: =C29/(1-E29) -> 3047.3081 | H29: =G29-F29 -> 203.15387
A30: 3 | B30: Com Desconto | C30: =E9 -> 2576.1859 | D30: =J9 -> 0.090506216 | E30: =K9 -> 0.2 | F30: =G9 -> 2832.5492 | G30: =C30/(1-E30) -> 3220.2324 | H30: =G30-F30 -> 387.68317

Sheet 💰 Quanto_Cobrar
A1: 💰 SIMULAÇÃO DE PRICING — PRÊMIO ALVO POR CLUSTER
A2: Com base nos custos médios por cluster e margem desejada, cada cliente recebe um prêmio alvo: Prêmio Alvo = Custo Médio do Cluster ÷ (1 − Margem Desejada)
A3: CLUSTER 0 | D3: CLUSTER 1 | G3: CLUSTER 2 | J3: CLUSTER 3
A4: Prêmio Alvo: R$ 2.512,53 | D4: Prêmio Alvo: R$ 6.328,04 | G4: Prêmio Alvo: R$ 3.047,31 | J4: Prêmio Alvo: R$ 3.220,23
A5: Margem: 25% | D5: Margem: 25% | G5: Margem: 30% | J5: Margem: 20%
A6: Cluster | B6: Idade | C6: IMC | D6: Nº Filhos | E6: Gênero | F6: Elegível Desconto | G6: Região | H6: Custo Médico (R$) | I6: Prêmio Atual (R$) | J6: Margem Alvo | K6: Prêmio Alvo (R$) | L6: Lucro c/ Novo Preço (R$) | M6: Lucro Atual (R$)
A7: 3 | B7: 19 | C7: female | D7: 24.1 | E7: 0 | F7: yes | G7: south | H7: 1483.2083 | I7: 1744.951 | J7: =VLOOKUP(A7,'📊 Análises'!$A$4:$K$10,11,0) -> 0.2 | K7: =H7/(1-J7) -> 1854.0104 | L7: =K7-H7 -> 370.80209 | M7: =I7-H7 -> 261.74265
A8: 0 | B8: 18 | C8: male | D8: 23.5 | E8: 1 | F8: no | G8: southeast | H8: 2237.6079 | I8: 2632.4799 | J8: =VLOOKUP(A8,'📊 Análises'!$A$4:$K$10,11,0) -> 0.25 | K8: =H8/(1-J8) -> 2983.4772 | L8: =K8-H8 -> 745.86931 | M8: =I8-H8 -> 394.87199
A9: 2 | B9: 28 | C9: male | D9: 33 | E9: 3 | F9: no | G9: southeast | H9: 2046.0872 | I9: 2728.1162 | J9: =VLOOKUP(A9,'📊 Análises'!$A$4:$K$10,11,0) -> 0.3 | K9: =H9/(1-J9) -> 2922.9817 | L9: =K9-H9 -> 876.8945 | M9: =I9-H9 -> 682.02905
A10: 0 | B10: 33 | C10: male | D10: 23.3 | E10: 0 | F10: no | G10: midwest | H10: 2331.692 | I10: 2743.1671 | J10: =VLOOKUP(A10,'📊 Análises'!$A$4:$K$10,11,0) -> 0.25 | K10: =H10/(1-J10) -> 3108.9227 | L10: =K10-H10 -> 777.23068 | M10: =I10-H10 -> 411.47507
A11: 0 | B11: 32 | C11: male | D11: 23.4 | E11: 0 | F11: no | G11: midwest | H11: 1942.5013 | I11: 2285.2956 | J11: =VLOOKUP(A11,'📊 Análises'!$A$4:$K$10,11,0) -> 0.25 | K11: =H11/(1-J11) -> 2590.0017 | L11: =K11-H11 -> 647.50042 | M11: =I11-H11 -> 342.79434
A12: 0 | B12: 31 | C12: female | D12: 22.9 | E12: 0 | F12: no | G12: southeast | H12: 2375.7405 | I12: 2794.9889 | J12: =VLOOKUP(A12,'📊 Análises'!$A$4:$K$10,11,0) -> 0.25 | K12: =H12/(1-J12) -> 3167.6541 | L12: =K12-H12 -> 791.91351 | M12: =I12-H12 -> 419.24833
A13: 1 | B13: 46 | C13: female | D13: 33.4 | E13: 1 | F13: no | G13: southeast | H13: 4453.2339 | I13: 4241.1752 | J13: =VLOOKUP(A13,'📊 Análises'!$A$4:$K$10,11,0) -> 0.25 | K13: =H13/(1-J13) -> 5937.6452 | L13: =K13-H13 -> 1484.4113 | M13: =I13-H13 -> -212.05876
A14: 2 | B14: 37 | C14: female | D14: 27.7 | E14: 3 | F14: no | G14: midwest | H14: 2326.6882 | I14: 3102.2509 | J14: =VLOOKUP(A14,'📊 Análises'!$A$4:$K$10,11,0) -> 0.3 | K14: =H14/(1-J14) -> 3323.8402 | L14: =K14-H14 -> 997.15207 | M14: =I14-H14 -> 775.56272
A15: 2 | B15: 37 | C15: male | D15: 29.8 | E15: 2 | F15: no | G15: northeast | H15: 1712.426 | I15: 2283.2346 | J15: =VLOOKUP(A15,'📊 Análises'!$A$4:$K$10,11,0) -> 0.3 | K15: =H15/(1-J15) -> 2446.3228 | L15: =K15-H15 -> 733.89685 | M15: =I15-H15 -> 570.80866
A16: 1 | B16: 60 | C16: female | D16: 25.8 | E16: 0 | F16: no | G16: midwest | H16: 4684.8206 | I16: 4461.7339 | J16: =VLOOKUP(A16,'📊 Análises'!$A$4:$K$10,11,0) -> 0.25 | K16: =H16/(1-J16) -> 6246.4275 | L16: =K16-H16 -> 1561.6069 | M16: =I16-H16 -> -223.08669
A17: 0 | B17: 25 | C17: male | D17: 20.3 | E17: 0 | F17: no | G17: northeast | H17: 2168.5565 | I17: 2551.2429 | J17: =VLOOKUP(A17,'📊 Análises'!$A$4:$K$10,11,0) -> 0.25 | K17: =H17/(1-J17) -> 2891.4087 | L17: =K17-H17 -> 722.85216 | M17: =I17-H17 -> 382.68644
A18: 3 | B18: 62 | C18: female | D18: 26.3 | E18: 0 | F18: yes | G18: southeast | H18: 5417.6353 | I18: 5159.6527 | J18: =VLOOKUP(A18,'📊 Análises'!$A$4:$K$10,11,0) -> 0.2 | K18: =H18/(1-J18) -> 6772.0441 | L18: =K18-H18 -> 1354.4088 | M18: =I18-H18 -> -257.98263
... A1344: 3 | B1344: 61 | C1344: female | D1344: 29.1 | E1344: 0 | F1344: yes | G1344: midwest | H1344: 4541.902 | I1344: 4325.6209 | J1344: =VLOOKUP(A1344,'📊 Análises'!$A$4:$K$10,11,0) -> 0.2 | K1344: =H1344/(1-J1344) -> 5677.3775 | L1344: =K1344-H1344 -> 1135.4755 | M1344: =I1344-H1344 -> -216.28105

Sheet 🆕 Novos_Clientes
A1: 🆕 CLASSIFICAÇÃO DE NOVOS CLIENTES
A2: Novos clientes são alocados ao cluster mais similar via K-Means, recebendo automaticamente o Prêmio Alvo correspondente ao seu perfil de risco.
A3: age | B3: gender | C3: bmi | D3: children | E3: discount_eligibility | F3: region | G3: expenses | H3: premium | I3: discount_eligibility_tratado | J3: Cluster Atribuído | K3: Prêmio Alvo (R$)
A4: 19 | B4: female | C4: 24.1 | D4: 0 | E4: yes | F4: south | G4: 1483.2083 | H4: 1744.951 | I4: 1 | J4: {=_xlfn._xlws.PY(6,0,Tabela_novos[#All])} -> 3 | K4: 3220.23
A5: 56 | B5: female | C5: 39.8 | D5: 0 | E5: no | F5: southeast | G5: 3641.0645 | H5: 3467.6805 | I5: 0 | J5: 1 | K5: 6328.04
A6: 28 | B6: male | C6: 33 | D6: 3 | E6: no | F6: southeast | G6: 2046.0872 | H6: 2728.1162 | I6: 0 | J6: 2 | K6: 3047.31
A9: ℹ️ Como funciona a classificação?
A10: 1. Os dados do novo cliente são padronizados com o mesmo StandardScaler treinado na base original.
A11: 2. O K-Means calcula a distância euclidiana do cliente aos 4 centroides e atribui ao cluster mais próximo.
A12: 3. Com o cluster definido, o sistema aplica automaticamente o Prêmio Alvo correspondente à margem desejada.
